Metadata-Version: 1.0
Name: django-indexer
Version: 0.3.0
Summary: Key/Value Indexer
Home-page: http://github.com/dcramer/django-indexer
Author: David Cramer
Author-email: dcramer@gmail.com
License: UNKNOWN
Platform: UNKNOWN
Classifier: Framework :: Django
Classifier: Intended Audience :: Developers
Classifier: Intended Audience :: System Administrators
Classifier: Operating System :: OS Independent
Classifier: Topic :: Software Development
